stheno/__init__.py
stheno/_version.py
stheno/autograd.py
stheno/jax.py
stheno/lazy.py
stheno/random.py
stheno/tensorflow.py
stheno/torch.py
stheno/mo/__init__.py
stheno/mo/adk.py
stheno/mo/infer.py
stheno/mo/input.py
stheno/mo/kernel.py
stheno/mo/mean.py
stheno/model/__init__.py
stheno/model/fdd.py
stheno/model/gp.py
stheno/model/measure.py
stheno/model/observations.py
tests/__init__.py
tests/test_lazy.py
tests/test_random.py
tests/util.py
tests/mo/__init__.py
tests/mo/test_adk.py
tests/mo/test_infer.py
tests/mo/test_kernel.py
tests/mo/test_mean.py
tests/model/__init__.py
tests/model/test_cases.py
tests/model/test_fdd.py
tests/model/test_gp.py
tests/model/test_model.py
tests/model/test_observations.py
tests/model/util.py
stheno-1.4.2.dist-info/LICENCE.txt
stheno-1.4.2.dist-info/METADATA
stheno-1.4.2.dist-info/WHEEL
stheno-1.4.2.dist-info/top_level.txt
stheno-1.4.2.dist-info/RECORD
