Metadata-Version: 2.1
Name: stheno
Version: 1.4.2
Summary: Implementation of Gaussian processes in Python
Home-page: https://github.com/wesselb/stheno
Author: Wessel Bruinsma
Author-email: wessel.p.bruinsma@gmail.com
License: MIT
Requires-Python: >=3.6
License-File: LICENCE.txt
Requires-Dist: numpy>=1.16
Requires-Dist: fdm>=0.5.0
Requires-Dist: algebra>=1
Requires-Dist: plum-dispatch>=2
Requires-Dist: backends>=1.4.11
Requires-Dist: backends-matrix>=1.2.11
Requires-Dist: mlkernels>=0.3.6
Requires-Dist: wbml>=0.4.0
